PyMyUtils_lixin1226/PyMyUtils2024.py
PyMyUtils_lixin1226/__init__.py
PyMyUtils2024-0.0.1.dist-info/LICENSE
PyMyUtils2024-0.0.1.dist-info/METADATA
PyMyUtils2024-0.0.1.dist-info/WHEEL
PyMyUtils2024-0.0.1.dist-info/top_level.txt
PyMyUtils2024-0.0.1.dist-info/RECORD
